protonvpn_cli_gui/__init__.py
protonvpn_cli_gui/__main__.py
protonvpn_cli_gui/about_screen.kv
protonvpn_cli_gui/about_screen.py
protonvpn_cli_gui/app_settings_screen.kv
protonvpn_cli_gui/app_settings_screen.py
protonvpn_cli_gui/connection_profiles_screen.kv
protonvpn_cli_gui/connection_profiles_screen.py
protonvpn_cli_gui/custombehaviors.py
protonvpn_cli_gui/devclasses.kv
protonvpn_cli_gui/main_screen.kv
protonvpn_cli_gui/main_screen.py
protonvpn_cli_gui/protonvpngui.kv
protonvpn_cli_gui/protonvpnguiapp.py
protonvpn_cli_gui/report_bug_screen.kv
protonvpn_cli_gui/report_bug_screen.py
protonvpn_cli_gui/vpn_settings_screen.kv
protonvpn_cli_gui/vpn_settings_screen.py
protonvpn_cli_gui/welcome_screen.kv
protonvpn_cli_gui/welcome_screen.py
protonvpn_cli_gui/widgets.kv
protonvpn_cli_gui/widgets.py
protonvpn_cli_gui/images/Screenshot from 2020-03-22 20-25-10.png
protonvpn_cli_gui/images/Screenshot from 2020-03-22 20-27-33.png
protonvpn_cli_gui/images/Screenshot from 2020-03-22 20-27-52.png
protonvpn_cli_gui/images/Screenshot from 2020-03-22 20-28-47.png
protonvpn_cli_gui/images/Screenshot from 2020-03-22 20-29-27.png
protonvpn_cli_gui/images/Screenshot from 2020-03-22 20-30-00.png
protonvpn_cli_gui/images/active-tab-content-panel.png
protonvpn_cli_gui/images/active-tab.png
protonvpn_cli_gui/images/bitrate-download-arrow.png
protonvpn_cli_gui/images/bitrate-upload-arrow.png
protonvpn_cli_gui/images/close-window-icon.png
protonvpn_cli_gui/images/connect-small-hover-transparent.png
protonvpn_cli_gui/images/connect-small-hover.png
protonvpn_cli_gui/images/connect-small-hover_150.png
protonvpn_cli_gui/images/connect-small_150.png
protonvpn_cli_gui/images/disconnect.png
protonvpn_cli_gui/images/disconnect_hover.png
protonvpn_cli_gui/images/disconnected_window.png
protonvpn_cli_gui/images/double-arrow-right-grey.png
protonvpn_cli_gui/images/dropdown-button-down.png
protonvpn_cli_gui/images/dropdown-button-up_no_underline.png
protonvpn_cli_gui-0.1.10.dist-info/LICENSE
protonvpn_cli_gui-0.1.10.dist-info/METADATA
protonvpn_cli_gui-0.1.10.dist-info/WHEEL
protonvpn_cli_gui-0.1.10.dist-info/entry_points.txt
protonvpn_cli_gui-0.1.10.dist-info/top_level.txt
protonvpn_cli_gui-0.1.10.dist-info/RECORD
